shef/__init__.py
shef/constants.py
shef/loaders/Readme.md
shef/loaders/__init__.py
shef/loaders/base_loader.py
shef/loaders/cda_loader.py
shef/loaders/dssvue_loader.py
shef/loaders/shared.py
shef/loaders/shefdss_util.py
shef/shef_parser.py
shef_parser-1.5.3.dist-info/METADATA
shef_parser-1.5.3.dist-info/WHEEL
shef_parser-1.5.3.dist-info/entry_points.txt
shef_parser-1.5.3.dist-info/licenses/LICENSE
shef_parser-1.5.3.dist-info/RECORD
