Metadata-Version: 2.4
Name: shef-parser
Version: 1.5.3
Summary: Module to extract data from SHEF formated files with ability to save output as flat file, dss file, or directly into Corps water management systems (CWMS) database
License: LICENSE
License-File: LICENSE
Keywords: SHEF,USACE,CWMS
Author: Hydrologic Engineering Center
Requires-Python: >=3.9,<4.0
Classifier: License :: Other/Proprietary License
Classifier: Programming Language :: Python :: 3
Classifier: Programming Language :: Python :: 3.9
Classifier: Programming Language :: Python :: 3.10
Classifier: Programming Language :: Python :: 3.11
Classifier: Programming Language :: Python :: 3.12
Classifier: Programming Language :: Python :: 3.13
Classifier: Programming Language :: Python :: 3.14
Project-URL: Repository, https://github.com/HydrologicEngineeringCenter/SHEF_processing
